pyramid_googleauth/__init__.py
pyramid_googleauth/_routes.py
pyramid_googleauth/exceptions.py
pyramid_googleauth/security.py
pyramid_googleauth/views.py
pyramid_googleauth/services/__init__.py
pyramid_googleauth/services/google_auth.py
pyramid_googleauth/templates/login_failure.html.jinja2
pyramid_googleauth-1.0.6.dist-info/LICENSE
pyramid_googleauth-1.0.6.dist-info/METADATA
pyramid_googleauth-1.0.6.dist-info/WHEEL
pyramid_googleauth-1.0.6.dist-info/top_level.txt
pyramid_googleauth-1.0.6.dist-info/RECORD
