Metadata-Version: 2.2
Name: pyramid-googleauth
Version: 1.0.6
Summary: 'Sign in with Google' for Pyramid.
Home-page: https://github.com/hypothesis/pyramid-googleauth
Project-URL: Repository, https://github.com/hypothesis/pyramid-googleauth
Project-URL: Issues, https://github.com/hypothesis/pyramid-googleauth/issues
Project-URL: Changelog, https://github.com/hypothesis/pyramid-googleauth/releases
Classifier: Programming Language :: Python :: 3
Classifier: License :: OSI Approved :: BSD License
Classifier: Intended Audience :: Developers
Requires-Python: >=3.8
License-File: LICENSE
Requires-Dist: google-auth-oauthlib
Requires-Dist: PyJWT
Requires-Dist: pyramid>=2.0.0
